Metadata-Version: 2.1
Name: wilayati
Version: 1.0.0
Summary: This Python module provides functionality for searching and retrieving information about Algerian Wilayas (provinces) and their respective Communes (municipalities).
Home-page: https://github.com/rabahdj2002/Wilayas-of-Algeria
Author: Rabah Djebbes
Author-email: rabahwork@gmail.com
Classifier: Programming Language :: Python :: 3
Classifier: License :: OSI Approved :: MIT License
Classifier: Operating System :: OS Independent
Requires-Python: >=3.6
License-File: LICENSE
